{
  "stats": {
    "suites": 1,
    "tests": 14,
    "passes": 0,
    "pending": 0,
    "failures": 14,
    "start": "2021-12-29T07:03:33.861Z",
    "end": "2021-12-29T07:08:09.608Z",
    "duration": 275747,
    "testsRegistered": 14,
    "passPercent": 0,
    "pendingPercent": 0,
    "other": 0,
    "hasOther": false,
    "skipped": 0,
    "hasSkipped": false
  },
  "results": [
    {
      "uuid": "ff49e1f0-fd0c-4a6d-acc5-117bacadde83",
      "title": "",
      "fullFile": "cypress/integration/Admin_Testcases/08_PatientCharts_Add_Edit_Delete.spec.js",
      "file": "cypress/integration/Admin_Testcases/08_PatientCharts_Add_Edit_Delete.spec.js",
      "beforeHooks": [],
      "afterHooks": [],
      "tests": [],
      "suites": [
        {
          "uuid": "147582d1-f600-462b-810f-4c45f0d422b0",
          "title": "Add/edit/delete family member testcases",
          "fullFile": "",
          "file": "",
          "beforeHooks": [],
          "afterHooks": [],
          "tests": [
            {
              "title": "As a Admin the should be navigated to the patient charts section by clicking on charts tab on patient profile of particular patient.",
              "fullTitle": "Add/edit/delete family member testcases As a Admin the should be navigated to the patient charts section by clicking on charts tab on patient profile of particular patient.",
              "timedOut": null,
              "duration": 64638,
              "state": "failed",
              "speed": null,
              "pass": false,
              "fail": true,
              "pending": false,
              "context": null,
              "code": "cy.login(cred.email, cred.password);\ncy.url().should('contain', '/patients');\ncy.get('.bg-white > .w-full').should('be.visible').type('pawankumar@yopmail.com');\ncy.wait(2000);\ncy.get('tr:nth-child(1) > td:nth-child(7) > div > svg:nth-child(1) > path:nth-child(1)').scrollIntoView().should('be.visible').click();\ncy.url().should('contain', '/address');\ncy.get('.border-transparent').should('be.visible').should('contain', 'Charts').click();\ncy.url().should('contain', '/charts');",
              "err": {
                "message": "AssertionError: Timed out retrying after 15000ms: Expected to find element: `//input[@name='email']`, but never found it.",
                "estack": "AssertionError: Timed out retrying after 15000ms: Expected to find element: `//input[@name='email']`, but never found it.\n    at Context.eval (https://staging.rch.build-release.com/__cypress/tests?p=cypress\\support\\index.js:251:6)",
                "diff": null
              },
              "uuid": "165fd812-2377-47cd-9d8e-fac8fbd9d028",
              "parentUUID": "147582d1-f600-462b-810f-4c45f0d422b0",
              "isHook": false,
              "skipped": false
            },
            {
              "title": "At Charts page each label and field should have proper label and validations",
              "fullTitle": "Add/edit/delete family member testcases At Charts page each label and field should have proper label and validations",
              "timedOut": null,
              "duration": 15250,
              "state": "failed",
              "speed": null,
              "pass": false,
              "fail": true,
              "pending": false,
              "context": null,
              "code": "cy.get('.font-medium > .inline').should('be.visible').should('have.text', 'Members');\ncy.get('.flex-wrap > .flex').should('be.visible').should('have.text', 'Add Another Member');\ncy.get(':nth-child(1) > .bg-white > .justify-between > .text-base').should('be.visible');\ncy.get('.h-screen>div:nth-child(2)>div:nth-child(1)').should('be.visible');\ncy.get(':nth-child(1) > .bg-white > .justify-between > .flex > .font-medium').should('be.visible').should('have.text', 'self');\ncy.get('.h-screen>div:nth-child(2)>div:nth-child(1)>div>div:nth-child(2)>div:nth-child(1)>div').should('be.visible').should('have.text', 'Date of Birth');\ncy.get('.h-screen>div:nth-child(2)>div:nth-child(1)>div>div:nth-child(2)>div:nth-child(2)>div').should('be.visible').should('have.text', 'Gender');",
              "err": {
                "message": "AssertionError: Timed out retrying after 15000ms: Expected to find element: `.font-medium > .inline`, but never found it.",
                "estack": "AssertionError: Timed out retrying after 15000ms: Expected to find element: `.font-medium > .inline`, but never found it.\n    at Context.eval (https://staging.rch.build-release.com/__cypress/tests?p=cypress\\integration\\Admin_Testcases\\08_PatientCharts_Add_Edit_Delete.spec.js:147:38)",
                "diff": null
              },
              "uuid": "4bad0e20-a118-4c50-93c8-95748ae02fe2",
              "parentUUID": "147582d1-f600-462b-810f-4c45f0d422b0",
              "isHook": false,
              "skipped": false
            },
            {
              "title": "As a Admin the user should able to get a pop up window of add family member by clicking on \"add another member\" button on charts page",
              "fullTitle": "Add/edit/delete family member testcases As a Admin the user should able to get a pop up window of add family member by clicking on \"add another member\" button on charts page",
              "timedOut": null,
              "duration": 15233,
              "state": "failed",
              "speed": null,
              "pass": false,
              "fail": true,
              "pending": false,
              "context": null,
              "code": "cy.get('.flex-wrap > .flex').should('be.visible').should('have.text', 'Add Another Member').click();",
              "err": {
                "message": "AssertionError: Timed out retrying after 15000ms: Expected to find element: `.flex-wrap > .flex`, but never found it.",
                "estack": "AssertionError: Timed out retrying after 15000ms: Expected to find element: `.flex-wrap > .flex`, but never found it.\n    at Context.eval (https://staging.rch.build-release.com/__cypress/tests?p=cypress\\integration\\Admin_Testcases\\08_PatientCharts_Add_Edit_Delete.spec.js:157:34)",
                "diff": null
              },
              "uuid": "7dce4ee5-02eb-41ec-bb6f-eeab8155da6d",
              "parentUUID": "147582d1-f600-462b-810f-4c45f0d422b0",
              "isHook": false,
              "skipped": false
            },
            {
              "title": "At add family member page each label and field have proper lable and validations",
              "fullTitle": "Add/edit/delete family member testcases At add family member page each label and field have proper lable and validations",
              "timedOut": null,
              "duration": 15236,
              "state": "failed",
              "speed": null,
              "pass": false,
              "fail": true,
              "pending": false,
              "context": null,
              "code": "cy.get('.hidden > .justify-between > .font-bold').should('be.visible').should('have.text', 'Add Family Member');\ncy.get('.hidden > .justify-between > .w-6').should('be.visible');\ncy.get('.hidden > .mt-6 > .px-4 > :nth-child(1) > :nth-child(1) > .text-sm > div').should('be.visible').should('have.text', 'First Name');\ncy.get('.hidden > .mt-6 > .px-4 > :nth-child(1) > :nth-child(2) > .text-sm > div').should('be.visible').should('have.text', 'Last Name');\ncy.get('.hidden > .mt-6 > .px-4 > :nth-child(2) > div.w-full > .text-sm > div').should('be.visible').should('have.text', 'Date of Birth');\ncy.get('.hidden > .mt-6 > .px-4 > :nth-child(2) > :nth-child(2) > .block').should('be.visible').should('have.text', 'Relationship');\ncy.get('.hidden > .mt-6 > .px-4 > :nth-child(3) > :nth-child(1) > .block').should('be.visible').should('have.text', 'Gender');\ncy.get('.hidden > .mt-6 > .px-4 > .pt-4 > .flex').should('be.visible').should('have.text', 'Add Member').click();\ncy.get(':nth-child(1) > :nth-child(1) > .text-red-600').should('be.visible').should('have.text', 'Required');\ncy.get(':nth-child(1) > :nth-child(2) > .text-red-600').should('be.visible').should('have.text', 'Required');\ncy.get(':nth-child(2) > :nth-child(1) > .text-red-600').should('be.visible').should('have.text', 'Required');\ncy.get(':nth-child(2) > :nth-child(2) > .text-red-600').should('be.visible').should('have.text', 'Required');\ncy.get(':nth-child(3) > :nth-child(1) > .text-red-600').should('be.visible').should('have.text', 'Required');",
              "err": {
                "message": "AssertionError: Timed out retrying after 15000ms: Expected to find element: `.hidden > .justify-between > .font-bold`, but never found it.",
                "estack": "AssertionError: Timed out retrying after 15000ms: Expected to find element: `.hidden > .justify-between > .font-bold`, but never found it.\n    at Context.eval (https://staging.rch.build-release.com/__cypress/tests?p=cypress\\integration\\Admin_Testcases\\08_PatientCharts_Add_Edit_Delete.spec.js:160:55)",
                "diff": null
              },
              "uuid": "db45b82b-8146-462d-abcb-0fb3c821eca2",
              "parentUUID": "147582d1-f600-462b-810f-4c45f0d422b0",
              "isHook": false,
              "skipped": false
            },
            {
              "title": "By filling add family member form and cliking on add member button the family member should be added",
              "fullTitle": "Add/edit/delete family member testcases By filling add family member form and cliking on add member button the family member should be added",
              "timedOut": null,
              "duration": 15264,
              "state": "failed",
              "speed": null,
              "pass": false,
              "fail": true,
              "pending": false,
              "context": null,
              "code": "cy.get('.hidden > .mt-6 > .px-4 > :nth-child(1) > :nth-child(1) > .relative > .appearance-none').should('be.visible').type('shiva');\ncy.get('.hidden > .mt-6 > .px-4 > :nth-child(1) > :nth-child(2) > .relative > .appearance-none').should('be.visible').type('Teja');\ncy.get('.hidden > .mt-6 > .px-4 > :nth-child(2) > div.w-full > .relative > .react-datepicker-wrapper > .react-datepicker__input-container > .appearance-none').should('be.visible').click();\ncy.get('.react-datepicker__year-select').select('1991');\ncy.get('.react-datepicker__day--012').should('be.visible').click();\ncy.get('.hidden > .mt-6 > .px-4 > :nth-child(2) > :nth-child(2) > .font-bold > .css-yk16xz-control').should('be.visible').click();\ncy.get('.css-11unzgr>div:nth-child(2)').click();\ncy.get('.hidden > .mt-6 > .px-4 > :nth-child(3) > :nth-child(1) > .font-bold > .css-yk16xz-control > .css-1hwfws3').should('be.visible').click();\ncy.get('.css-11unzgr>div:nth-child(2)').click();\ncy.get('.hidden > .mt-6 > .px-4 > .pt-4 > .flex').should('be.visible').should('have.text', 'Add Member').click();\ncy.contains('Family Member Added successfully');",
              "err": {
                "message": "AssertionError: Timed out retrying after 15000ms: Expected to find element: `.hidden > .mt-6 > .px-4 > :nth-child(1) > :nth-child(1) > .relative > .appearance-none`, but never found it.",
                "estack": "AssertionError: Timed out retrying after 15000ms: Expected to find element: `.hidden > .mt-6 > .px-4 > :nth-child(1) > :nth-child(1) > .relative > .appearance-none`, but never found it.\n    at Context.eval (https://staging.rch.build-release.com/__cypress/tests?p=cypress\\integration\\Admin_Testcases\\08_PatientCharts_Add_Edit_Delete.spec.js:175:102)",
                "diff": null
              },
              "uuid": "14930ed2-da1f-4515-935b-2f5589742d40",
              "parentUUID": "147582d1-f600-462b-810f-4c45f0d422b0",
              "isHook": false,
              "skipped": false
            },
            {
              "title": "The added family member should refelect under charts section",
              "fullTitle": "Add/edit/delete family member testcases The added family member should refelect under charts section",
              "timedOut": null,
              "duration": 15247,
              "state": "failed",
              "speed": null,
              "pass": false,
              "fail": true,
              "pending": false,
              "context": null,
              "code": "cy.get(':nth-child(3) > .bg-white > .justify-between > .text-base').should('be.visible').should('have.text', 'shiva teja');\ncy.get('.h-screen>div:nth-child(2)>div:nth-child(3)>div>div:nth-child(2)>div:nth-child(2)>span').should('be.visible').should('have.text', 'Female');\ncy.logout();",
              "err": {
                "message": "AssertionError: Timed out retrying after 15000ms: Expected to find element: `:nth-child(3) > .bg-white > .justify-between > .text-base`, but never found it.",
                "estack": "AssertionError: Timed out retrying after 15000ms: Expected to find element: `:nth-child(3) > .bg-white > .justify-between > .text-base`, but never found it.\n    at Context.eval (https://staging.rch.build-release.com/__cypress/tests?p=cypress\\integration\\Admin_Testcases\\08_PatientCharts_Add_Edit_Delete.spec.js:188:73)",
                "diff": null
              },
              "uuid": "cd1fb6fe-2f2c-4333-b7b8-88a04d0f7976",
              "parentUUID": "147582d1-f600-462b-810f-4c45f0d422b0",
              "isHook": false,
              "skipped": false
            },
            {
              "title": "As a Admin the user can edit the details of the family member by clicking on edit icon against the particular member",
              "fullTitle": "Add/edit/delete family member testcases As a Admin the user can edit the details of the family member by clicking on edit icon against the particular member",
              "timedOut": null,
              "duration": 21943,
              "state": "failed",
              "speed": null,
              "pass": false,
              "fail": true,
              "pending": false,
              "context": null,
              "code": "cy.login(cred.email, cred.password);\ncy.url().should('contain', '/patients');\ncy.get('.bg-white > .w-full').should('be.visible').type('pawankumar@yopmail.com');\ncy.wait(2000);\ncy.get('tr:nth-child(1) > td:nth-child(7) > div > svg:nth-child(1) > path:nth-child(1)').scrollIntoView().should('be.visible').click();\ncy.url().should('contain', '/address');\ncy.get('.border-transparent').should('be.visible').should('contain', 'Charts').click();\ncy.url().should('contain', '/charts');\ncy.get('.h-screen>div:nth-child(2)>div:nth-child(3)').should('be.visible');\ncy.get(':nth-child(3) > .bg-white > .justify-between > .flex > :nth-child(3)').should('be.visible').click();",
              "err": {
                "message": "AssertionError: Timed out retrying after 15000ms: Expected to find element: `//input[@name='email']`, but never found it.",
                "estack": "AssertionError: Timed out retrying after 15000ms: Expected to find element: `//input[@name='email']`, but never found it.\n    at Context.eval (https://staging.rch.build-release.com/__cypress/tests?p=cypress\\support\\index.js:251:6)",
                "diff": null
              },
              "uuid": "30a8da6a-ab19-4dbf-a225-d840434a9c54",
              "parentUUID": "147582d1-f600-462b-810f-4c45f0d422b0",
              "isHook": false,
              "skipped": false
            },
            {
              "title": "At Edit family member window each label and field have proper lable and validations",
              "fullTitle": "Add/edit/delete family member testcases At Edit family member window each label and field have proper lable and validations",
              "timedOut": null,
              "duration": 15265,
              "state": "failed",
              "speed": null,
              "pass": false,
              "fail": true,
              "pending": false,
              "context": null,
              "code": "cy.get('.hidden > .justify-between > .font-bold').should('be.visible').should('have.text', 'Edit Family Member');\ncy.get('.hidden > .justify-between > .w-6').should('be.visible');\ncy.get('.hidden > .mt-6 > .px-4 > :nth-child(1) > :nth-child(1) > .text-sm > div').should('be.visible').should('have.text', 'First Name');\ncy.get('.hidden > .mt-6 > .px-4 > :nth-child(1) > :nth-child(2) > .text-sm > div').should('be.visible').should('have.text', 'Last Name');\ncy.get('.hidden > .mt-6 > .px-4 > :nth-child(2) > div.w-full > .text-sm > div').should('be.visible').should('have.text', 'Date of Birth');\ncy.get('.hidden > .mt-6 > .px-4 > :nth-child(2) > :nth-child(2) > .block').should('be.visible').should('have.text', 'Relationship');\ncy.get('.hidden > .mt-6 > .px-4 > :nth-child(3) > :nth-child(1) > .block').should('be.visible').should('have.text', 'Gender');\ncy.get('.hidden > .mt-6 > .px-4 > .pt-4 > .flex').should('be.visible').should('have.text', 'Save Details');",
              "err": {
                "message": "AssertionError: Timed out retrying after 15000ms: Expected to find element: `.hidden > .justify-between > .font-bold`, but never found it.",
                "estack": "AssertionError: Timed out retrying after 15000ms: Expected to find element: `.hidden > .justify-between > .font-bold`, but never found it.\n    at Context.eval (https://staging.rch.build-release.com/__cypress/tests?p=cypress\\integration\\Admin_Testcases\\08_PatientCharts_Add_Edit_Delete.spec.js:206:55)",
                "diff": null
              },
              "uuid": "a448256a-0457-428b-8ae2-e581f73dca52",
              "parentUUID": "147582d1-f600-462b-810f-4c45f0d422b0",
              "isHook": false,
              "skipped": false
            },
            {
              "title": "After editing the family member details the user can save details by clicking save details button",
              "fullTitle": "Add/edit/delete family member testcases After editing the family member details the user can save details by clicking save details button",
              "timedOut": null,
              "duration": 15282,
              "state": "failed",
              "speed": null,
              "pass": false,
              "fail": true,
              "pending": false,
              "context": null,
              "code": "cy.get('.hidden > .mt-6 > .px-4 > :nth-child(1) > :nth-child(1) > .relative > .appearance-none').should('be.visible').clear().type('Nanda');\ncy.get('.hidden > .mt-6 > .px-4 > :nth-child(1) > :nth-child(2) > .relative > .appearance-none').should('be.visible').clear().type('Kishore');\ncy.get('.hidden > .mt-6 > .px-4 > :nth-child(2) > div.w-full > .relative > .react-datepicker-wrapper > .react-datepicker__input-container > .appearance-none').should('be.visible').click();\ncy.get('.react-datepicker__day--010').should('be.visible').click();\ncy.get('.hidden > .mt-6 > .px-4 > :nth-child(2) > :nth-child(2) > .font-bold > .css-yk16xz-control').should('be.visible').click();\ncy.xpath('//*[@id=\"react-select-2-option-0\"]').click();\ncy.get('.hidden > .mt-6 > .px-4 > :nth-child(3) > :nth-child(1) > .font-bold > .css-yk16xz-control > .css-1hwfws3').should('be.visible').click();\ncy.get('#react-select-3-option-0').click();\ncy.get('.hidden > .mt-6 > .px-4 > .pt-4 > .flex').should('be.visible').should('have.text', 'Save Details').click();\ncy.contains('Family Member Updated Successfully');\ncy.wait(2000);",
              "err": {
                "message": "AssertionError: Timed out retrying after 15000ms: Expected to find element: `.hidden > .mt-6 > .px-4 > :nth-child(1) > :nth-child(1) > .relative > .appearance-none`, but never found it.",
                "estack": "AssertionError: Timed out retrying after 15000ms: Expected to find element: `.hidden > .mt-6 > .px-4 > :nth-child(1) > :nth-child(1) > .relative > .appearance-none`, but never found it.\n    at Context.eval (https://staging.rch.build-release.com/__cypress/tests?p=cypress\\integration\\Admin_Testcases\\08_PatientCharts_Add_Edit_Delete.spec.js:216:102)",
                "diff": null
              },
              "uuid": "479a8fa9-c5ba-4a58-acc4-c199e28ade0c",
              "parentUUID": "147582d1-f600-462b-810f-4c45f0d422b0",
              "isHook": false,
              "skipped": false
            },
            {
              "title": "The edited details should be refelected under charts section",
              "fullTitle": "Add/edit/delete family member testcases The edited details should be refelected under charts section",
              "timedOut": null,
              "duration": 15273,
              "state": "failed",
              "speed": null,
              "pass": false,
              "fail": true,
              "pending": false,
              "context": null,
              "code": "cy.get(':nth-child(3) > .bg-white > .justify-between > .text-base').should('be.visible').should('have.text', 'nanda kishore');\ncy.get('.h-screen>div:nth-child(2)>div:nth-child(3)>div>div:nth-child(2)>div:nth-child(2)>span').should('be.visible').should('have.text', 'Male');",
              "err": {
                "message": "AssertionError: Timed out retrying after 15000ms: Expected to find element: `:nth-child(3) > .bg-white > .justify-between > .text-base`, but never found it.",
                "estack": "AssertionError: Timed out retrying after 15000ms: Expected to find element: `:nth-child(3) > .bg-white > .justify-between > .text-base`, but never found it.\n    at Context.eval (https://staging.rch.build-release.com/__cypress/tests?p=cypress\\integration\\Admin_Testcases\\08_PatientCharts_Add_Edit_Delete.spec.js:229:73)",
                "diff": null
              },
              "uuid": "8b0ed6d7-f0ff-46fb-a2e0-bcbedc295de6",
              "parentUUID": "147582d1-f600-462b-810f-4c45f0d422b0",
              "isHook": false,
              "skipped": false
            },
            {
              "title": "As a Admin the user can able to delete a family member by clicking on delete icon on particular member",
              "fullTitle": "Add/edit/delete family member testcases As a Admin the user can able to delete a family member by clicking on delete icon on particular member",
              "timedOut": null,
              "duration": 15274,
              "state": "failed",
              "speed": null,
              "pass": false,
              "fail": true,
              "pending": false,
              "context": null,
              "code": "cy.get('.h-screen>div:nth-child(2)>div:nth-child(3)').should('be.visible');\ncy.get(':nth-child(3) > .bg-white > .justify-between > .flex > :nth-child(2)').should('be.visible').click();",
              "err": {
                "message": "AssertionError: Timed out retrying after 15000ms: Expected to find element: `.h-screen>div:nth-child(2)>div:nth-child(3)`, but never found it.",
                "estack": "AssertionError: Timed out retrying after 15000ms: Expected to find element: `.h-screen>div:nth-child(2)>div:nth-child(3)`, but never found it.\n    at Context.eval (https://staging.rch.build-release.com/__cypress/tests?p=cypress\\integration\\Admin_Testcases\\08_PatientCharts_Add_Edit_Delete.spec.js:234:59)",
                "diff": null
              },
              "uuid": "6b2aea3a-8dcc-4443-a890-bfa5c8cb41ec",
              "parentUUID": "147582d1-f600-462b-810f-4c45f0d422b0",
              "isHook": false,
              "skipped": false
            },
            {
              "title": "At delete member confirmation window each label and field have proper lable and validations",
              "fullTitle": "Add/edit/delete family member testcases At delete member confirmation window each label and field have proper lable and validations",
              "timedOut": null,
              "duration": 15281,
              "state": "failed",
              "speed": null,
              "pass": false,
              "fail": true,
              "pending": false,
              "context": null,
              "code": "cy.get('.mb-4 > .font-bold').should('be.visible').should('have.text', 'Confirmation');\ncy.get('.hidden > .mb-4 > .w-6').should('be.visible');\ncy.get('.hidden > :nth-child(2) > .shadow-corner > .bg-white > .justify-between > .text-primary').should('be.visible').should('have.text', 'nanda kishore');\ncy.get('.hidden > :nth-child(2) > .shadow-corner > .bg-white > .justify-between > .flex > .font-medium').should('be.visible').should('have.text', 'son');\ncy.get('body > div:nth-child(7)>div>div>div:nth-child(1)>div>div:nth-child(1)>div>div>div:nth-child(1)>div').should('be.visible').should('have.text', 'Date of Birth');\ncy.get('body > div:nth-child(7)>div>div>div:nth-child(1)>div>div:nth-child(1)>div>div>div:nth-child(2)>div').should('be.visible').should('have.text', 'Gender');\ncy.get('body > div:nth-child(7)>div>div>div:nth-child(1)>div>div:nth-child(1)>div>div>div:nth-child(2)>span:nth-child(2)').should('be.visible').should('have.text', 'Male');\ncy.get('.hidden > :nth-child(2) > .items-center.mt-6 > .flex').should('be.visible').should('have.text', 'Are you sure, you want to remove this member?');\ncy.get('.hidden > :nth-child(2) > .mb-3 > .flex').should('be.visible').should('have.text', 'Remove');",
              "err": {
                "message": "AssertionError: Timed out retrying after 15000ms: Expected to find element: `.mb-4 > .font-bold`, but never found it.",
                "estack": "AssertionError: Timed out retrying after 15000ms: Expected to find element: `.mb-4 > .font-bold`, but never found it.\n    at Context.eval (https://staging.rch.build-release.com/__cypress/tests?p=cypress\\integration\\Admin_Testcases\\08_PatientCharts_Add_Edit_Delete.spec.js:238:34)",
                "diff": null
              },
              "uuid": "de1b472c-c780-466f-917a-687467afbef5",
              "parentUUID": "147582d1-f600-462b-810f-4c45f0d422b0",
              "isHook": false,
              "skipped": false
            },
            {
              "title": "By clicking on remove button on confirmation window the family member should be deleted",
              "fullTitle": "Add/edit/delete family member testcases By clicking on remove button on confirmation window the family member should be deleted",
              "timedOut": null,
              "duration": 15286,
              "state": "failed",
              "speed": null,
              "pass": false,
              "fail": true,
              "pending": false,
              "context": null,
              "code": "cy.get('.hidden > :nth-child(2) > .mb-3 > .flex').should('be.visible').should('have.text', 'Remove').click();\ncy.contains('Family Member Deleted Successfully');",
              "err": {
                "message": "AssertionError: Timed out retrying after 15000ms: Expected to find element: `.hidden > :nth-child(2) > .mb-3 > .flex`, but never found it.",
                "estack": "AssertionError: Timed out retrying after 15000ms: Expected to find element: `.hidden > :nth-child(2) > .mb-3 > .flex`, but never found it.\n    at Context.eval (https://staging.rch.build-release.com/__cypress/tests?p=cypress\\integration\\Admin_Testcases\\08_PatientCharts_Add_Edit_Delete.spec.js:249:55)",
                "diff": null
              },
              "uuid": "5d7b716b-6c67-47db-a995-1038768dfc24",
              "parentUUID": "147582d1-f600-462b-810f-4c45f0d422b0",
              "isHook": false,
              "skipped": false
            },
            {
              "title": "The deleted member should not reflect under charts section",
              "fullTitle": "Add/edit/delete family member testcases The deleted member should not reflect under charts section",
              "timedOut": null,
              "duration": 15319,
              "state": "failed",
              "speed": null,
              "pass": false,
              "fail": true,
              "pending": false,
              "context": null,
              "code": "cy.get('.flex-wrap > .font-medium').should('be.visible').should('have.text', '2 Members');\ncy.logout();",
              "err": {
                "message": "AssertionError: Timed out retrying after 15000ms: Expected to find element: `.flex-wrap > .font-medium`, but never found it.",
                "estack": "AssertionError: Timed out retrying after 15000ms: Expected to find element: `.flex-wrap > .font-medium`, but never found it.\n    at Context.eval (https://staging.rch.build-release.com/__cypress/tests?p=cypress\\integration\\Admin_Testcases\\08_PatientCharts_Add_Edit_Delete.spec.js:253:41)",
                "diff": null
              },
              "uuid": "a87ed095-a1b1-404e-b6ad-486574e45f3b",
              "parentUUID": "147582d1-f600-462b-810f-4c45f0d422b0",
              "isHook": false,
              "skipped": false
            }
          ],
          "suites": [],
          "passes": [],
          "failures": [
            "165fd812-2377-47cd-9d8e-fac8fbd9d028",
            "4bad0e20-a118-4c50-93c8-95748ae02fe2",
            "7dce4ee5-02eb-41ec-bb6f-eeab8155da6d",
            "db45b82b-8146-462d-abcb-0fb3c821eca2",
            "14930ed2-da1f-4515-935b-2f5589742d40",
            "cd1fb6fe-2f2c-4333-b7b8-88a04d0f7976",
            "30a8da6a-ab19-4dbf-a225-d840434a9c54",
            "a448256a-0457-428b-8ae2-e581f73dca52",
            "479a8fa9-c5ba-4a58-acc4-c199e28ade0c",
            "8b0ed6d7-f0ff-46fb-a2e0-bcbedc295de6",
            "6b2aea3a-8dcc-4443-a890-bfa5c8cb41ec",
            "de1b472c-c780-466f-917a-687467afbef5",
            "5d7b716b-6c67-47db-a995-1038768dfc24",
            "a87ed095-a1b1-404e-b6ad-486574e45f3b"
          ],
          "pending": [],
          "skipped": [],
          "duration": 269791,
          "root": false,
          "rootEmpty": false,
          "_timeout": 2000
        }
      ],
      "passes": [],
      "failures": [],
      "pending": [],
      "skipped": [],
      "duration": 0,
      "root": true,
      "rootEmpty": true,
      "_timeout": 2000
    }
  ],
  "meta": {
    "mocha": {
      "version": "7.0.1"
    },
    "mochawesome": {
      "options": {
        "quiet": false,
        "reportFilename": "report",
        "saveHtml": true,
        "saveJson": true,
        "consoleReporter": "spec",
        "useInlineDiffs": false,
        "code": true
      },
      "version": "7.0.1"
    },
    "marge": {
      "options": {
        "reportDir": "cypress/reports",
        "reportFilename": "report",
        "overwrite": false,
        "html": true,
        "json": true,
        "charts": true
      },
      "version": "6.0.1"
    }
  }
}